rtl/alu.sv
module alu #(
    parameter WIDTH = 32
)(
    input  logic                 clk,
    input  logic                 rst_n,
    input  logic [WIDTH-1:0]     operand_a,
    input  logic [WIDTH-1:0]     operand_b,
    input  logic [3:0]           alu_ctrl,
    output logic [WIDTH-1:0]     alu_result,
    output logic                 zero_flag
);

    always_ff @(posedge clk or negedge rst_n) begin
        if (!rst_n) begin
            alu_result <= '0;
        end else begin
            case (alu_ctrl)
                4'b0000: alu_result <= operand_a + operand_b; // ADD
                4'b0001: alu_result <= operand_a - operand_b; // SUB
                4'b0010: alu_result <= operand_a & operand_b; // AND
                4'b0011: alu_result <= operand_a | operand_b; // OR
                4'b0100: alu_result <= operand_a ^ operand_b; // XOR
                4'b0101: alu_result <= operand_a << operand_b[4:0]; // SLL
                4'b0110: alu_result <= operand_a >> operand_b[4:0]; // SRL
                default: alu_result <= '0;
            endcase
        end
    end

    assign zero_flag = (alu_result == 0);

endmodule

tb/alu_tb.sv
module alu_tb;

    logic clk;
    logic rst_n;
    logic [31:0] a, b;
    logic [3:0] alu_ctrl;
    logic [31:0] result;
    logic zero;

    alu dut (
        .clk(clk),
        .rst_n(rst_n),
        .operand_a(a),
        .operand_b(b),
        .alu_ctrl(alu_ctrl),
        .alu_result(result),
        .zero_flag(zero)
    );

    always #5 clk = ~clk;

    initial begin
        // waveform dump
        $dumpfile("dump.vcd");
        $dumpvars(0, alu_tb);

        clk = 0;
        rst_n = 0;
        #10 rst_n = 1;

        // ADD
        a = 10; b = 20; alu_ctrl = 4'b0000;
        #10;

        // SUB
        a = 30; b = 10; alu_ctrl = 4'b0001;
        #10;

        // AND
        a = 32'hF0F0; b = 32'h0FF0; alu_ctrl = 4'b0010;
        #10;

        // SHIFT LEFT
        a = 32'h1; b = 5; alu_ctrl = 4'b0101;
        #10;

        $finish;
    end

endmodule

dump.vcd
$date
	Thu Feb  5 15:42:03 2026
$end
$version
	Icarus Verilog
$end
$timescale
	1s
$end
$scope module alu_tb $end
$var wire 1 ! zero $end
$var wire 32 " result [31:0] $end
$var reg 32 # a [31:0] $end
$var reg 4 $ alu_ctrl [3:0] $end
$var reg 32 % b [31:0] $end
$var reg 1 & clk $end
$var reg 1 ' rst_n $end
$scope module dut $end
$var wire 4 ( alu_ctrl [3:0] $end
$var wire 1 & clk $end
$var wire 32 ) operand_a [31:0] $end
$var wire 32 * operand_b [31:0] $end
$var wire 1 ' rst_n $end
$var wire 1 ! zero_flag $end
$var parameter 32 + WIDTH $end
$var reg 32 , alu_result [31:0] $end
$upscope $end
$upscope $end
$enddefinitions $end
$comment Show the parameter values. $end
$dumpall
b100000 +
$end
#0
$dumpvars
b0 ,
bx *
bx )
bx (
0'
0&
bx %
bx $
bx #
b0 "
1!
$end
#5
1&
#10
0&
b0 $
b0 (
b10100 %
b10100 *
b1010 #
b1010 )
1'
#15
0!
b11110 "
b11110 ,
1&
#20
0&
b1 $
b1 (
b1010 %
b1010 *
b11110 #
b11110 )
#25
b10100 "
b10100 ,
1&
#30
0&
b10 $
b10 (
b111111110000 %
b111111110000 *
b1111000011110000 #
b1111000011110000 )
#35
b11110000 "
b11110000 ,
1&
#40
0&
b101 $
b101 (
b101 %
b101 *
b1 #
b1 )
#45
b100000 "
b100000 ,
1&
